faststream_prometheus/__init__.py
faststream_prometheus/collectors.py
faststream_prometheus/middlewares.py
faststream_prometheus-0.1.5.dist-info/LICENSE
faststream_prometheus-0.1.5.dist-info/METADATA
faststream_prometheus-0.1.5.dist-info/WHEEL
faststream_prometheus-0.1.5.dist-info/RECORD
