Metadata-Version: 2.1
Name: faststream-prometheus
Version: 0.1.5
Summary: FastStream Based Metrics Collection for Prometheus
Home-page: https://projects.rocshers.com/open-source/faststream-prometheus
License: MIT
Keywords: faststream,prometheus
Author: Aleksei Marusich
Author-email: aleksei.marusich@rocshers.com
Requires-Python: >=3.9,<4
Classifier: Intended Audience :: Developers
Classifier: Intended Audience :: Information Technology
Classifier: Intended Audience :: System Administrators
Classifier: License :: OSI Approved :: MIT License
Classifier: Programming Language :: Python
Classifier: Programming Language :: Python :: 3
Classifier: Programming Language :: Python :: 3.9
Classifier: Programming Language :: Python :: 3.10
Classifier: Programming Language :: Python :: 3.11
Classifier: Programming Language :: Python :: 3.12
Classifier: Programming Language :: Python :: 3 :: Only
Classifier: Programming Language :: Python :: 3.8
Classifier: Topic :: Software Development :: Libraries
Classifier: Topic :: Software Development :: Libraries :: Python Modules
Classifier: Topic :: System :: Archiving :: Packaging
Classifier: Topic :: System :: Software Distribution
Requires-Dist: faststream
Requires-Dist: prometheus-client
Requires-Dist: prometheus-client-utils
Project-URL: Documentation, https://projects.rocshers.com/open-source/faststream-prometheus/docs
Project-URL: Repository, https://gitlab.com/rocshers/python/faststream-prometheus
